CppHeaderParser/CppHeaderParser.py
CppHeaderParser/__init__.py
CppHeaderParser/doxygen.py
CppHeaderParser/lexer.py
CppHeaderParser/tojson.py
CppHeaderParser/version.py
robotpy_cppheaderparser-5.1.2.dist-info/LICENSE.txt
robotpy_cppheaderparser-5.1.2.dist-info/METADATA
robotpy_cppheaderparser-5.1.2.dist-info/WHEEL
robotpy_cppheaderparser-5.1.2.dist-info/top_level.txt
robotpy_cppheaderparser-5.1.2.dist-info/RECORD
