Metadata-Version: 1.2
Name: robotpy-cppheaderparser
Version: 5.1.2
Summary: Parse C++ header files and generate a data structure representing the class
Home-page: https://github.com/robotpy/robotpy-cppheaderparser
Author: Jashua Cloutier
Author-email: jashuac@bellsouth.net
Maintainer: RobotPy Development Team
Maintainer-email: robotpy@googlegroups.com
License: BSD
Keywords: c++ header parser ply
Platform: Platform Independent
Classifier: Operating System :: OS Independent
Classifier: Programming Language :: Python
Classifier: Programming Language :: Python :: 2
Classifier: Programming Language :: Python :: 3
Classifier: Programming Language :: C++
Classifier: License :: OSI Approved :: BSD License
Classifier: Development Status :: 5 - Production/Stable
Classifier: Intended Audience :: Developers
Classifier: Topic :: Software Development
Classifier: Topic :: Software Development :: Code Generators
Classifier: Topic :: Software Development :: Compilers
Classifier: Topic :: Software Development :: Disassemblers
Requires: ply
